cifrus/__init__.py
cifrus/cifrus.py
cifrus-1.0.4.dist-info/METADATA
cifrus-1.0.4.dist-info/WHEEL
cifrus-1.0.4.dist-info/licenses/LICENSE
cifrus-1.0.4.dist-info/RECORD
