Metadata-Version: 2.3
Name: cifrus
Version: 1.0.4
Summary: Official implementation of Class-invariante Feature Range Uniform Sampling (CiFRUS)
Project-URL: Homepage, https://github.com/sakhawathossain/CiFRUS
Project-URL: Issues, https://github.com/sakhawathossain/CiFRUS/issues
Author: Sakhawat Hossain Saimon, Tanzira Najnin, Jianhua Ruan
Maintainer-email: Sakhawat Hossain Saimon <sakhawathossain.saimon@utsa.edu>
License-File: LICENSE
Classifier: Operating System :: OS Independent
Classifier: Programming Language :: Python :: 3
Requires-Python: >=3.9
Requires-Dist: numpy
Requires-Dist: scipy
